caprice/__init__.py
caprice/config.py
caprice/document.py
caprice/page.py
caprice/primitives.py
caprice/utils.py
caprice/version.py
caprice/data/caprice/afm/Courier-Bold.afm
caprice/data/caprice/afm/Courier-BoldOblique.afm
caprice/data/caprice/afm/Courier-Oblique.afm
caprice/data/caprice/afm/Courier.afm
caprice/data/caprice/afm/Helvetica-Bold.afm
caprice/data/caprice/afm/Helvetica-BoldOblique.afm
caprice/data/caprice/afm/Helvetica-Oblique.afm
caprice/data/caprice/afm/Helvetica.afm
caprice/data/caprice/afm/Symbol.afm
caprice/data/caprice/afm/Times-Bold.afm
caprice/data/caprice/afm/Times-BoldItalic.afm
caprice/data/caprice/afm/Times-Italic.afm
caprice/data/caprice/afm/Times-Roman.afm
caprice/data/caprice/afm/ZapfDingbats.afm
caprice/data/caprice/encoding/glyphlist.txt
caprice/data/caprice/encoding/zapfdingbats.txt
caprice/font/__init__.py
caprice/font/font.py
caprice/font/latin_chars.py
caprice/font/encoding/__init__.py
caprice/font/encoding/base.py
caprice/font/encoding/glyph_list.py
caprice/font/encoding/win_ansi_encoding.py
caprice/font/encoding/zapf_dingbats_encoding.py
caprice/font/type1/__init__.py
caprice/font/type1/font.py
caprice-0.1.3.dist-info/METADATA
caprice-0.1.3.dist-info/WHEEL
caprice-0.1.3.dist-info/top_level.txt
caprice-0.1.3.dist-info/RECORD
